{
  "active": true,
  "password_required": true,
  "users": {
    "uid_953228": { "name": "30$", "password": "12345" },
    "uid_436562": { "name": "Muhammad Yaqoob", "password": "@10$" },
    "uid_194444": { "name": "704", "password": "@123" },
    "uid_581143": { "name": "tang kr rha ", "password": "123" },
    "uid_131708": { "name": "Ms Trader replacement Done", "password": "10k" },
    "uid_314004": { "name": "2nd laptop", "password": "123" },
    "uid_449140": { "name": "Kabir 8k 2 Feb", "password": "123" },
    "QX_3c99997a9dcab31f": { "name": "Done 349", "password": "123" },
    "uid_390481": { "name": "4176k", "password": "123" },
    "uid_314084": { "name": "2nd laptop", "password": "123" },
    "uid_565734": { "name": "11k", "password": "123" },
    "uid_613375": { "name": "vaddah 35$", "password": "30$" },
    "uid_360663": { "name": "Danyal 5k", "password": "786" },
    "uid_471647": { "name": " 072", "password": "123" },
    "uid_609701": { "name": "aisha977", "password": "123" },
    "uid_790812": { "name": "3k ", "password": "123" },
    "uid_420217": { "name": "replacement Done ✅", "password": "123" },
    "Uid_796261": { "name": "10k", "password": "123" },
    "uid_700300": { "name": "101", "password": "123" },
    "uid_398222": { "name": "mehar", "password": "123" },
    "uid_000000": { "name": "bilalnix300pro", "password": "123" },
    "uid_300011": { "name": "TraderA2", "password": "PassA2" },
    "uid_706726": { "name": "10k", "password": "123" },
    "uid_267569": { "name": "Imran zayan ", "password": "123" },
    "uid_196869": { "name": "Maryam Trader 10", "password": "123" },
    "uid_819292": { "name": "8k", "password": "123" },
    "uid_922711": { "name": "Momin 10K 🇵🇰✅", "password": "123" },
    "uid_665723": { "name": "943 10k", "password": "123" },

    "uid_900001": { "name": "Customer1", "password": "123" },
    "uid_900002": { "name": "Customer2", "password": "123" },
    "uid_900003": { "name": "Customer3", "password": "123" },
    "uid_900004": { "name": "Customer4", "password": "123" },
    "uid_900005": { "name": "Customer5", "password": "123" },
    "uid_900006": { "name": "Customer6", "password": "123" },
    "uid_900007": { "name": "Customer7", "password": "123" },
    "uid_900008": { "name": "Customer8", "password": "123" },
    "uid_900009": { "name": "Customer9", "password": "123" },
    "uid_900010": { "name": "Customer10", "password": "123" },
    "uid_900011": { "name": "Customer11", "password": "123" },
    "uid_900012": { "name": "Customer12", "password": "123" },
    "uid_900013": { "name": "Customer13", "password": "123" },
    "uid_900014": { "name": "Customer14", "password": "123" },
    "uid_900015": { "name": "Customer15", "password": "123" },
    "uid_900016": { "name": "Customer16", "password": "123" },
    "uid_900017": { "name": "Customer17", "password": "123" },
    "uid_900018": { "name": "Customer18", "password": "123" },
    "uid_900019": { "name": "Customer19", "password": "123" },
    "uid_900020": { "name": "Customer20", "password": "123" },
    "uid_900021": { "name": "Customer21", "password": "123" },
    "uid_900022": { "name": "Customer22", "password": "123" },
    "uid_900023": { "name": "Customer23", "password": "123" },
    "uid_900024": { "name": "Customer24", "password": "123" },
    "uid_900025": { "name": "Customer25", "password": "123" },
    "uid_900026": { "name": "Customer26", "password": "123" },
    "uid_900027": { "name": "Customer27", "password": "123" },
    "uid_900028": { "name": "Customer28", "password": "123" },
    "uid_368350": { "name": "72", "password": "123" },
    "uid_510621": { "name": "asad", "password": "123" },
    "uid_661856": { "name": "broken", "password": "123" },
    "uid_887461": { "name": "brokendp50$", "password": "123" },
    "uid_972087": { "name": "943", "password": "123" },
    "uid_804747": { "name": "waqas", "password": "123" },
    "uid_526867": { "name": "50$243", "password": "123" },
    "uid_426034": { "name": "10kFasihurrehman", "password": "123" },
    "uid_466487": { "name": "lastreplace417", "password": "123" },
    "uid_236956": { "name": "tanver243laptop", "password": "123" },
    "uid_826037": { "name": "243tanverr", "password": "123" },
    "uid_829868": { "name": "ahmedali10k047", "password": "123" },
    "uid_972081": { "name": "saim4k", "password": "123" },
    "QX_GYDI72": { "name": "saimiphone10k", "password": "123" },
    "uid_905700": { "name": "saim16210k", "password": "123" },
    "uid_672951": { "name": "muzamil", "password": "123" },
    "uid_912146": { "name": "mughees123", "password": "123" },
    "uid_840441": { "name": "Mugheesurehman124", "password": "123" },
    "uid_781353": { "name": "muzimil964", "password": "123" },
    "uid_858219": { "name": "4176k", "password": "123" },
    "uid_968652": { "name": "iqram", "password": "123" },
    "uid_713100": { "name": "X300pro", "password": "123" }
  }
}